rtl/alu.v
// alu.v - 8-bit Arithmetic Logic Unit
// Performs ADD, SUB, AND, OR operations

module alu (
    input  [7:0] a,        // Operand A
    input  [7:0] b,        // Operand B
    input  [1:0] alu_op,   // Operation select
    output reg [7:0] result // ALU result
);

    // ALU operation codes
    localparam ADD = 2'b00;
    localparam SUB = 2'b01;
    localparam AND = 2'b10;
    localparam OR  = 2'b11;

    // Combinational logic for ALU operations
    always @(*) begin
        case (alu_op)
            ADD: result = a + b;
            SUB: result = a - b;
            AND: result = a & b;
            OR:  result = a | b;
            default: result = 8'h00;
        endcase
    end

endmodule

tb/alu_tb.v
// alu_tb.v - Testbench for ALU module

`timescale 1ns/1ps

module alu_tb;

    // Testbench signals
    reg  [7:0] a;
    reg  [7:0] b;
    reg  [1:0] alu_op;
    wire [7:0] result;

    // Instantiate ALU
    alu uut (
        .a(a),
        .b(b),
        .alu_op(alu_op),
        .result(result)
    );

    // Test procedure
    initial begin
        $dumpfile("alu_tb.vcd");
        $dumpvars(0, alu_tb);

        $display("Starting ALU testbench...");
        $display("Time\tOP\tA\tB\tResult\tExpected");
        $display("----\t--\t--\t--\t------\t--------");

        // Test ADD
        alu_op = 2'b00; a = 8'd15; b = 8'd10; #10;
        $display("%0t\tADD\t%d\t%d\t%d\t%d %s", $time, a, b, result, 8'd25, 
                 (result == 8'd25) ? "PASS" : "FAIL");

        alu_op = 2'b00; a = 8'd255; b = 8'd1; #10;
        $display("%0t\tADD\t%d\t%d\t%d\t%d %s", $time, a, b, result, 8'd0, 
                 (result == 8'd0) ? "PASS (overflow)" : "FAIL");

        // Test SUB
        alu_op = 2'b01; a = 8'd20; b = 8'd5; #10;
        $display("%0t\tSUB\t%d\t%d\t%d\t%d %s", $time, a, b, result, 8'd15, 
                 (result == 8'd15) ? "PASS" : "FAIL");

        alu_op = 2'b01; a = 8'd5; b = 8'd10; #10;
        $display("%0t\tSUB\t%d\t%d\t%d\t%d %s", $time, a, b, result, 8'd251, 
                 (result == 8'd251) ? "PASS (underflow)" : "FAIL");

        // Test AND
        alu_op = 2'b10; a = 8'hF0; b = 8'h0F; #10;
        $display("%0t\tAND\t%h\t%h\t%h\t%h %s", $time, a, b, result, 8'h00, 
                 (result == 8'h00) ? "PASS" : "FAIL");

        alu_op = 2'b10; a = 8'hFF; b = 8'hAA; #10;
        $display("%0t\tAND\t%h\t%h\t%h\t%h %s", $time, a, b, result, 8'hAA, 
                 (result == 8'hAA) ? "PASS" : "FAIL");

        // Test OR
        alu_op = 2'b11; a = 8'hF0; b = 8'h0F; #10;
        $display("%0t\tOR\t%h\t%h\t%h\t%h %s", $time, a, b, result, 8'hFF, 
                 (result == 8'hFF) ? "PASS" : "FAIL");

        alu_op = 2'b11; a = 8'h00; b = 8'h00; #10;
        $display("%0t\tOR\t%h\t%h\t%h\t%h %s", $time, a, b, result, 8'h00, 
                 (result == 8'h00) ? "PASS" : "FAIL");

        $display("\nALU testbench complete!");
        $finish;
    end

endmodule

alu_tb.vcd
$date
	Fri Mar 27 21:05:46 2026
$end
$version
	Icarus Verilog
$end
$timescale
	1ps
$end
$scope module alu_tb $end
$var wire 8 ! result [7:0] $end
$var reg 8 " a [7:0] $end
$var reg 2 # alu_op [1:0] $end
$var reg 8 $ b [7:0] $end
$scope module uut $end
$var wire 8 % a [7:0] $end
$var wire 2 & alu_op [1:0] $end
$var wire 8 ' b [7:0] $end
$var parameter 2 ( ADD $end
$var parameter 2 ) AND $end
$var parameter 2 * OR $end
$var parameter 2 + SUB $end
$var reg 8 , result [7:0] $end
$upscope $end
$upscope $end
$enddefinitions $end
$comment Show the parameter values. $end
$dumpall
b1 +
b11 *
b10 )
b0 (
$end
#0
$dumpvars
b11001 ,
b1010 '
b0 &
b1111 %
b1010 $
b0 #
b1111 "
b11001 !
$end
#10000
b0 !
b0 ,
b1 $
b1 '
b11111111 "
b11111111 %
#20000
b1111 !
b1111 ,
b101 $
b101 '
b10100 "
b10100 %
b1 #
b1 &
#30000
b11111011 !
b11111011 ,
b1010 $
b1010 '
b101 "
b101 %
#40000
b0 !
b0 ,
b1111 $
b1111 '
b11110000 "
b11110000 %
b10 #
b10 &
#50000
b10101010 !
b10101010 ,
b10101010 $
b10101010 '
b11111111 "
b11111111 %
#60000
b11111111 !
b11111111 ,
b1111 $
b1111 '
b11110000 "
b11110000 %
b11 #
b11 &
#70000
b0 !
b0 ,
b0 $
b0 '
b0 "
b0 %
